jccrypto/__init__.py
jccrypto-1.4.2.dist-info/METADATA
jccrypto-1.4.2.dist-info/WHEEL
jccrypto-1.4.2.dist-info/top_level.txt
jccrypto-1.4.2.dist-info/RECORD
