Metadata-Version: 2.1
Name: jccrypto
Version: 1.4.2
Summary: Simple crypto library
Home-page: https://github.com/lang-library/py-jccrypto
Author: JavaCommons Technologies
Author-email: javacommmons@gmail.com
License: MIT
Classifier: Programming Language :: Python
Classifier: Programming Language :: Python :: 3
Classifier: Programming Language :: Python :: 3.4
Classifier: Programming Language :: Python :: 3.5
Classifier: Programming Language :: Python :: 3.6
Requires-Dist: PyCryptoDome
